sphinxcontrib_aafig2-1.2-py3.7-nspkg.pth
sphinxcontrib/aafig-pre-sphinx-trans.py
sphinxcontrib/aafig-pre-transform.py
sphinxcontrib/aafig.py
sphinxcontrib_aafig2-1.2.dist-info/LICENSE
sphinxcontrib_aafig2-1.2.dist-info/METADATA
sphinxcontrib_aafig2-1.2.dist-info/WHEEL
sphinxcontrib_aafig2-1.2.dist-info/namespace_packages.txt
sphinxcontrib_aafig2-1.2.dist-info/top_level.txt
sphinxcontrib_aafig2-1.2.dist-info/RECORD
