Metadata-Version: 2.1
Name: sphinxcontrib-aafig2
Version: 1.2
Summary: aafig Sphinx extension
Home-page: http://packages.python.org/sphinxcontrib-aafig/
Author: Leandro Lucarella
Author-email: llucax@gmail.com
License: BOLA
Download-URL: http://pypi.python.org/pypi/sphinxcontrib-aafig
Platform: any
Classifier: Development Status :: 5 - Production/Stable
Classifier: Environment :: Console
Classifier: Environment :: Web Environment
Classifier: Intended Audience :: Developers
Classifier: License :: Public Domain
Classifier: Operating System :: OS Independent
Classifier: Programming Language :: Python
Classifier: Topic :: Documentation
Classifier: Topic :: Utilities
Requires-Dist: Sphinx (>=0.6)
Requires-Dist: aafigure (>=0.3)
